ac_app_deploy/__init__.py
ac_app_deploy/deploy.py
ac_app_installer/__init__.py
ac_app_installer/install.py
appfire_connect_sdk-1.8.0.dist-info/METADATA
appfire_connect_sdk-1.8.0.dist-info/WHEEL
appfire_connect_sdk-1.8.0.dist-info/entry_points.txt
appfire_connect_sdk-1.8.0.dist-info/top_level.txt
appfire_connect_sdk-1.8.0.dist-info/RECORD
