Metadata-Version: 2.1
Name: appfire-connect-sdk
Version: 1.8.0
Summary: SDK for creating and deploying appfire connect apps
Home-page: https://bitbucket.org/appfire/ac-app-installer/src/master/
Author: Steven Kling
Author-email: steven.kling@appfire.com
License: MIT
Platform: UNKNOWN
Classifier: License :: OSI Approved :: MIT License
Classifier: Programming Language :: Python :: 3
Requires-Dist: click
Requires-Dist: funcy
Requires-Dist: PyYAML
Requires-Dist: questionary
Requires-Dist: coloredlogs
Requires-Dist: pyngrok
Requires-Dist: boto3
